tensorflow_lite_support/__init__.py
tensorflow_lite_support/cc/__init__.py
tensorflow_lite_support/cc/task/__init__.py
tensorflow_lite_support/cc/task/core/__init__.py
tensorflow_lite_support/cc/task/core/proto/__init__.py
tensorflow_lite_support/cc/task/core/proto/external_file_pb2.py
tensorflow_lite_support/cc/task/processor/__init__.py
tensorflow_lite_support/cc/task/processor/proto/__init__.py
tensorflow_lite_support/cc/task/processor/proto/bounding_box_pb2.py
tensorflow_lite_support/cc/task/processor/proto/class_pb2.py
tensorflow_lite_support/cc/task/processor/proto/classification_options_pb2.py
tensorflow_lite_support/cc/task/processor/proto/classifications_pb2.py
tensorflow_lite_support/cc/task/processor/proto/detection_options_pb2.py
tensorflow_lite_support/cc/task/processor/proto/detections_pb2.py
tensorflow_lite_support/cc/task/processor/proto/embedding_options_pb2.py
tensorflow_lite_support/cc/task/processor/proto/embedding_pb2.py
tensorflow_lite_support/cc/task/processor/proto/search_options_pb2.py
tensorflow_lite_support/cc/task/processor/proto/search_result_pb2.py
tensorflow_lite_support/cc/task/processor/proto/segmentation_options_pb2.py
tensorflow_lite_support/cc/task/vision/__init__.py
tensorflow_lite_support/cc/task/vision/proto/__init__.py
tensorflow_lite_support/cc/task/vision/proto/segmentations_pb2.py
tensorflow_lite_support/codegen/__init__.py
tensorflow_lite_support/codegen/python/__init__.py
tensorflow_lite_support/codegen/python/_pywrap_codegen.so
tensorflow_lite_support/codegen/python/codegen.py
tensorflow_lite_support/metadata/__init__.py
tensorflow_lite_support/metadata/metadata_schema.fbs
tensorflow_lite_support/metadata/metadata_schema_py_generated.py
tensorflow_lite_support/metadata/schema_py_generated.py
tensorflow_lite_support/metadata/cc/__init__.py
tensorflow_lite_support/metadata/cc/python/__init__.py
tensorflow_lite_support/metadata/cc/python/_pywrap_metadata_version.so
tflite_support-0.4.1.dist-info/LICENSE
tflite_support-0.4.1.dist-info/METADATA
tflite_support-0.4.1.dist-info/WHEEL
tflite_support-0.4.1.dist-info/entry_points.txt
tflite_support-0.4.1.dist-info/top_level.txt
tflite_support-0.4.1.dist-info/RECORD
